helios_gpu_controller/HeliosGPUController.py
helios_gpu_controller/__init__.py
helios_gpu_controller/test.py
helios_gpu_controller/utils.py
HeliosGPUController-2.0.1.dist-info/LICENSE
HeliosGPUController-2.0.1.dist-info/METADATA
HeliosGPUController-2.0.1.dist-info/WHEEL
HeliosGPUController-2.0.1.dist-info/top_level.txt
HeliosGPUController-2.0.1.dist-info/RECORD
