Metadata-Version: 2.1
Name: HeliosGPUController
Version: 2.0.1
Summary: Helios GPU Controller dynamically reduces Graphics Processing Unit (GPU) clock speeds by leveraging insights from the current energy mix and meteorological data. Data is obtained by the SMARD API and Forecast.Solar. The goal is to reduce power consumption of non-renewable sources.
Author-email: Lasse Mueller <mueller.lasse.ltd@gmail.com>, Bao Nguyen <baotrani@yahoo.de>, Berkehan Unal <unal@tnt.uni-hannover.de>
Requires-Python: >=3.8
License-File: LICENSE
Requires-Dist: PyYAML ~=6.0.1
Requires-Dist: requests ~=2.31.0
Requires-Dist: geocoder ~=1.38.1
Requires-Dist: pytz ~=2023.3.post1
Requires-Dist: numpy ~=1.26.2
Requires-Dist: matplotlib ~=3.8.2
Requires-Dist: timezonefinder ~=6.4.0
Requires-Dist: suntime ~=1.2.5
Requires-Dist: geopy ~=2.4.1
